__init__.py
nxtree/__init__.py
nxtree/tree.py
nxtree-0.0.2.dist-info/licenses/LICENSE
nxtree-0.0.2.dist-info/METADATA
nxtree-0.0.2.dist-info/WHEEL
nxtree-0.0.2.dist-info/top_level.txt
nxtree-0.0.2.dist-info/RECORD
